logycon_pipeline/__init__.py
logycon_pipeline/pipeline.py
logycon_pipeline-0.1.0.dist-info/METADATA
logycon_pipeline-0.1.0.dist-info/WHEEL
logycon_pipeline-0.1.0.dist-info/RECORD
